{
  "name": "Foo::Bar",
  "source-url": null,
  "support": {
    "source": null
  },
  "perl": "6",
  "resources": [
    
  ],
  "build-depends": [
    
  ],
  "auth": "github:tbrowder",
  "depends": [
    
  ],
  "tags": [
    "ecosystem",
    "META6",
    "module"
  ],
  "license": "Artistic-2.0",
  "test-depends": [
    "Test::Meta"
  ],
  "provides": {
    "Foo::Bar": "lib/Foo/Bar.pm6"
  },
  "version": "72.0.1",
  "authors": [
    "Tom Browder <tom.browder@gmail.com>"
  ],
  "description": "Miscellaneous stuff for practicing module development",
  "meta6": "0"
}